hello.py
hello_world_alex-0.0.1.dist-info/DESCRIPTION.rst
hello_world_alex-0.0.1.dist-info/METADATA
hello_world_alex-0.0.1.dist-info/RECORD
hello_world_alex-0.0.1.dist-info/WHEEL
hello_world_alex-0.0.1.dist-info/entry_points.txt
hello_world_alex-0.0.1.dist-info/metadata.json
hello_world_alex-0.0.1.dist-info/top_level.txt
