Metadata-Version: 2.0
Name: hello-world-alex
Version: 0.0.1
Summary: An utility to display a name
Home-page: https://github.com/alexcviek/hello_world_alex
Author: Alex Cwiek
Author-email: alex@wegotpop.com
License: MIT
Platform: UNKNOWN
